README.rst
setup.py
django_multimedia_basic_chat.egg-info/PKG-INFO
django_multimedia_basic_chat.egg-info/SOURCES.txt
django_multimedia_basic_chat.egg-info/dependency_links.txt
django_multimedia_basic_chat.egg-info/requires.txt
django_multimedia_basic_chat.egg-info/top_level.txt
multimedia_chat/__init__.py
multimedia_chat/admin.py
multimedia_chat/apps.py
multimedia_chat/models.py
multimedia_chat/serializers.py
multimedia_chat/solr_utils.py
multimedia_chat/system_error.py
multimedia_chat/tests.py
multimedia_chat/urls.py
multimedia_chat/utils.py
multimedia_chat/views.py