Metadata-Version: 1.0
Name: django-multimedia-basic-chat
Version: 0.0
Summary: A example django chat package
Home-page: https://github.com/faizans-cuelogic/django-multimedia-basic-chat/
Author: Faizan Shaikh
Author-email: faizan.shaikh308@gmail.com
License: MIT
Platform: UNKNOWN
